stringology/__init__.py
stringology/ac.py
stringology/ac2.py
stringology/align.py
stringology/ed.py
stringology/gaps.py
stringology/lcs.py
stringology/lis.py
stringology/ngrams.py
stringology/text.py
stringology-0.1.0.dist-info/DESCRIPTION.rst
stringology-0.1.0.dist-info/METADATA
stringology-0.1.0.dist-info/RECORD
stringology-0.1.0.dist-info/WHEEL
stringology-0.1.0.dist-info/entry_points.txt
stringology-0.1.0.dist-info/metadata.json
stringology-0.1.0.dist-info/top_level.txt
